{"cameraMode":{"drawMode":0,"name":"Shaded","section":"Shading Mode"},"sceneLighting":true,"audioPlay":false,"sceneViewState":{"showFog":true,"showMaterialUpdate":false,"showSkybox":true,"showFlares":true,"showImageEffects":true,"showParticleSystems":true},"in2DMode":false,"pivot":{"x":200.8110809326172,"y":183.5458221435547,"z":124.8779067993164},"rotation":{"x":0.1846160739660263,"y":-0.01601421646773815,"z":0.0031065023504197599,"w":0.9827190041542053},"size":594.6024169921875,"orthographic":false}